{"id":"379","players":[{"id":"3534","name":"Roy Carroll","position":"Goalkeeper","dateOfBirth":"Sep 30, 1977","age":"28","nationality":["Northern Ireland"],"currentClub":"Retired","height":"1,89m","foot":"right","joinedOn":"Jul 1, 2005","signedFrom":"Manchester United","marketValue":"€2.70m"},{"id":"3873","name":"Stephen Bywater","position":"Goalkeeper","dateOfBirth":"Jun 7, 1981","age":"25","nationality":["England"],"currentClub":"Retired","height":"1,89m","foot":"right","joinedOn":"Feb 20, 1998","signedFrom":"Rochdale AFC","marketValue":"€1.20m"},{"id":"4175","name":"Shaka Hislop","position":"Goalkeeper","dateOfBirth":"Feb 22, 1969","age":"37","nationality":["Trinidad and Tobago","England"],"currentClub":"Retired","height":"1,98m","foot":"right","joinedOn":"Jul 1, 2005","signedFrom":": Ablöse free transfer","marketValue":"€950k"},{"id":"46746","name":"Jimmy Walker","position":"Goalkeeper","dateOfBirth":"Jul 9, 1973","age":"32","nationality":["England"],"currentClub":"Retired","height":"1,80m","joinedOn":"Jul 1, 2004","signedFrom":": Ablöse free transfer","marketValue":"€600k"},{"id":"39035","name":"Matthew Reed","position":"Goalkeeper","dateOfBirth":"Dec 24, 1986","age":"19","nationality":["England"],"currentClub":"Without Club","height":"1,83m","joinedOn":"Jul 1, 2005","signedFrom":": Ablöse -","marketValue":"€50k"},{"id":"3698","name":"Anton Ferdinand","position":"Centre-Back","dateOfBirth":"Feb 18, 1985","age":"21","nationality":["England","St. Lucia"],"currentClub":"Retired","height":"1,85m","foot":"right","joinedOn":"Jul 1, 2003","signedFrom":": Ablöse -","marketValue":"€3.50m"},{"id":"3647","name":"Tomas Repka","position":"Centre-Back","dateOfBirth":"Jan 2, 1974","age":"32","nationality":["Czech Republic"],"currentClub":"Retired","height":"1,82m","foot":"right","joinedOn":"Aug 26, 2001","signedFrom":": Ablöse €8.25m","marketValue":"€2.50m"},{"id":"3799","name":"Christian Dailly","position":"Centre-Back","dateOfBirth":"Oct 23, 1973","age":"32","nationality":["Scotland"],"currentClub":"Retired","height":"1,83m","foot":"right","joinedOn":"Jan 30, 2001","signedFrom":"Blackburn Rovers","marketValue":"€2.00m"},{"id":"15838","name":"Elliott Ward","position":"Centre-Back","dateOfBirth":"Jan 19, 1985","age":"21","nationality":["England"],"currentClub":"Retired","height":"1,85m","foot":"right","joinedOn":"Jul 1, 2004","signedFrom":": Ablöse -","marketValue":"€1.25m"},{"id":"12709","name":"Danny Gabbidon","position":"Centre-Back","dateOfBirth":"Aug 8, 1979","age":"26","nationality":["Wales","Jamaica"],"currentClub":"Retired","height":"1,78m","foot":"right","joinedOn":"Jul 5, 2005","signedFrom":": Ablöse €2.00m","marketValue":"€1.00m"},{"id":"12691","name":"James Collins","position":"Centre-Back","dateOfBirth":"Aug 23, 1983","age":"22","nationality":["Wales"],"currentClub":"Retired","height":"1,88m","foot":"right","joinedOn":"Aug 1, 2012","signedFrom":": Ablöse €3.20m","marketValue":"€500k"},{"id":"3296","name":"Paul Konchesky","position":"Left-Back","dateOfBirth":"May 15, 1981","age":"25","nationality":["England"],"currentClub":"Retired","height":"1,78m","foot":"left","joinedOn":"Jul 5, 2005","signedFrom":"Charlton Athletic","marketValue":"€4.00m"},{"id":"13558","name":"Clive Clarke","position":"Left-Back","dateOfBirth":"Jan 14, 1980","age":"26","nationality":["Ireland"],"currentClub":"Retired","height":"1,80m","foot":"left","joinedOn":"Aug 1, 2005","signedFrom":"Stoke City","marketValue":"€400k"},{"id":"7499","name":"Lionel Scaloni","position":"Right-Back","dateOfBirth":"May 16, 1978","age":"28","nationality":["Argentina","Italy"],"currentClub":"Retired","height":"1,82m","foot":"right","joinedOn":"Jan 31, 2006","signedFrom":"Deportivo de La Coruña","marketValue":"€4.00m"},{"id":"14060","name":"Nigel Reo-Coker","position":"Defensive Midfield","dateOfBirth":"May 14, 1984","age":"22","nationality":["England","Sierra Leone"],"currentClub":"Retired","height":"1,75m","foot":"right","joinedOn":"Jan 22, 2004","signedFrom":": Ablöse €750k","marketValue":"€3.50m"},{"id":"23370","name":"Carl Fletcher","position":"Defensive Midfield","dateOfBirth":"Apr 7, 1980","age":"26","nationality":["Wales","England"],"currentClub":"Retired","height":"1,75m","foot":"right","joinedOn":"Aug 31, 2004","signedFrom":": Ablöse €410k","marketValue":"€750k"},{"id":"14052","name":"Hayden Mullins","position":"Defensive Midfield","dateOfBirth":"Mar 27, 1979","age":"27","nationality":["England"],"currentClub":"Retired","height":"1,82m","foot":"right","joinedOn":"Jul 1, 2003","signedFrom":": Ablöse free transfer","marketValue":"€700k"},{"id":"31835","name":"Mark Noble","position":"Central Midfield","dateOfBirth":"May 8, 1987","age":"19","nationality":["England","Ireland"],"currentClub":"Retired","height":"1,80m","foot":"right","joinedOn":"Jan 1, 2005","signedFrom":": Ablöse -","marketValue":"€800k"},{"id":"15835","name":"Chris Cohen","position":"Central Midfield","dateOfBirth":"Mar 5, 1987","age":"19","nationality":["England","Israel"],"currentClub":"Retired","height":"1,78m","foot":"left","joinedOn":"Jul 1, 2003","signedFrom":": Ablöse -","marketValue":"€50k"},{"id":"9171","name":"Shaun Newton","position":"Right Midfield","dateOfBirth":"Aug 20, 1975","age":"30","nationality":["England"],"currentClub":"Retired","height":"1,74m","foot":"right","joinedOn":"Jan 1, 2007","signedFrom":"Disqualification","marketValue":"€500k"},{"id":"3788","name":"Matthew Etherington","position":"Left Midfield","dateOfBirth":"Aug 14, 1981","age":"24","nationality":["England"],"currentClub":"Retired","height":"1,78m","foot":"left","joinedOn":"Aug 1, 2003","signedFrom":": Ablöse ?","marketValue":"€3.00m"},{"id":"31883","name":"Hogan Ephraim","position":"Left Midfield","dateOfBirth":"Mar 31, 1988","age":"18","nationality":["England"],"currentClub":"Retired","height":"1,75m","foot":"left","marketValue":"€100k"},{"id":"24475","name":"Yaniv Katan","position":"Attacking Midfield","dateOfBirth":"Jan 27, 1981","age":"25","nationality":["Israel"],"currentClub":"Retired","height":"1,85m","foot":"right","joinedOn":"Jan 1, 2006","signedFrom":": Ablöse €145k","marketValue":"€500k"},{"id":"27816","name":"Gavin Williams","position":"Attacking Midfield","dateOfBirth":"Jul 20, 1980","age":"25","nationality":["Wales"],"currentClub":"Heolgerrig Red Lion Community","height":"1,78m","foot":"right","joinedOn":"Dec 8, 2004","signedFrom":": Ablöse €375k","marketValue":"€400k"},{"id":"39709","name":"Kyel Reid","position":"Left Winger","dateOfBirth":"Nov 26, 1987","age":"18","nationality":["England","Jamaica"],"currentClub":"Rayners Lane FC","height":"1,78m","foot":"left","joinedOn":"Jul 1, 2005","signedFrom":": Ablöse -","marketValue":"€50k"},{"id":"7858","name":"Yossi Benayoun","position":"Right Winger","dateOfBirth":"May 5, 1980","age":"26","nationality":["Israel"],"currentClub":"Retired","height":"1,75m","foot":"right","joinedOn":"Aug 31, 2012","signedFrom":"Chelsea FC","marketValue":"€4.50m"},{"id":"14168","name":"Dean Ashton","position":"Centre-Forward","dateOfBirth":"Nov 24, 1983","age":"22","nationality":["England"],"currentClub":"Retired","height":"1,85m","foot":"right","joinedOn":"Jan 1, 2006","signedFrom":": Ablöse €10.89m","marketValue":"€10.00m"},{"id":"10011","name":"Marlon Harewood","position":"Centre-Forward","dateOfBirth":"Aug 25, 1979","age":"26","nationality":["England","Barbados"],"currentClub":"Retired","height":"1,85m","foot":"right","joinedOn":"Nov 25, 2003","signedFrom":": Ablöse €725k","marketValue":"€5.50m"},{"id":"4205","name":"Bobby Zamora","position":"Centre-Forward","dateOfBirth":"Jan 16, 1981","age":"25","nationality":["England","Trinidad and Tobago"],"currentClub":"Retired","height":"1,84m","foot":"left","joinedOn":"Jan 1, 2004","signedFrom":": Ablöse free transfer","marketValue":"€3.50m"},{"id":"3115","name":"David Bellion","position":"Centre-Forward","dateOfBirth":"Nov 27, 1982","age":"23","nationality":["France","Senegal"],"currentClub":"Retired","height":"1,81m","foot":"right","joinedOn":"Aug 17, 2005","signedFrom":"Manchester United","marketValue":"€2.25m"},{"id":"3266","name":"Jérémie Aliadière","position":"Centre-Forward","dateOfBirth":"Mar 30, 1983","age":"23","nationality":["France","Algeria"],"currentClub":"Retired","height":"1,83m","foot":"right","joinedOn":"Aug 25, 2005","signedFrom":": Ablöse free transfer","marketValue":"€1.25m"},{"id":"3392","name":"Teddy Sheringham","position":"Centre-Forward","dateOfBirth":"Apr 2, 1966","age":"40","nationality":["England"],"currentClub":"Retired","joinedOn":"Jul 14, 2004","signedFrom":": Ablöse free transfer","marketValue":"€500k"},{"id":"39034","name":"Tony Stokes","position":"Centre-Forward","dateOfBirth":"Jan 7, 1987","age":"19","nationality":["England"],"currentClub":"Hullbridge Sports FC","height":"1,86m","foot":"right","joinedOn":"Jul 1, 2005","signedFrom":": Ablöse -","marketValue":"€50k"}],"updatedAt":"2024-11-11T02:24:16.195005"}