{"id":"29","players":[{"id":"3584","name":"Paul Gerrard","position":"Goalkeeper","dateOfBirth":"Jan 22, 1973","age":"31","nationality":["England"],"currentClub":"Retired","height":"1,88m","foot":"left","joinedOn":"Jul 1, 1996","signedFrom":": Ablöse €1.50m"},{"id":"3120","name":"Richard Wright","position":"Goalkeeper","dateOfBirth":"Nov 5, 1977","age":"26","nationality":["England"],"currentClub":"Retired","height":"1,90m","foot":"right","joinedOn":"Jul 1, 2002","signedFrom":": Ablöse €5.50m"},{"id":"3583","name":"Steve Simonsen","position":"Goalkeeper","dateOfBirth":"Apr 3, 1979","age":"25","nationality":["England","Denmark"],"currentClub":"Retired","height":"1,87m","foot":"right","joinedOn":"Jul 1, 1998","signedFrom":": Ablöse €4.95m"},{"id":"3629","name":"Nigel Martyn","position":"Goalkeeper","dateOfBirth":"Aug 11, 1966","age":"37","nationality":["England"],"currentClub":"Retired","height":"1,88m","foot":"right","joinedOn":"Sep 1, 2003","signedFrom":"Leeds United"},{"id":"3582","name":"Iain Turner","position":"Goalkeeper","dateOfBirth":"Jan 26, 1984","age":"20","nationality":["Scotland"],"currentClub":"Retired","height":"1,93m","foot":"right","joinedOn":"Jul 1, 2003","signedFrom":"Stirling Albion FC"},{"id":"3472","name":"Alan Stubbs","position":"Centre-Back","dateOfBirth":"Oct 6, 1971","age":"32","nationality":["England"],"currentClub":"Retired","joinedOn":"Jan 1, 2006","signedFrom":"Sunderland AFC"},{"id":"3312","name":"David Weir","position":"Centre-Back","dateOfBirth":"May 10, 1970","age":"34","nationality":["Scotland"],"currentClub":"Retired","height":"1,91m","foot":"right","joinedOn":"Feb 1, 1999","signedFrom":"Heart of Midlothian FC"},{"id":"3270","name":"Joseph Yobo","position":"Centre-Back","dateOfBirth":"Sep 6, 1980","age":"23","nationality":["Nigeria","England"],"currentClub":"Retired","height":"1,88m","foot":"right","joinedOn":"Jul 1, 2003","signedFrom":": Ablöse €6.00m"},{"id":"25201","name":"Peter Clarke","position":"Centre-Back","dateOfBirth":"Jan 3, 1982","age":"22","nationality":["England"],"currentClub":"Warrington Town","height":"1,88m","foot":"right","joinedOn":"Jan 1, 2002","signedFrom":"Everton FC Reserves"},{"id":"3588","name":"Alessandro Pistone","position":"Left-Back","dateOfBirth":"Jul 27, 1975","age":"28","nationality":["Italy"],"currentClub":"Retired","height":"1,80m","foot":"both","joinedOn":"Jul 1, 2000","signedFrom":"Newcastle United"},{"id":"3272","name":"David Unsworth","position":"Left-Back","dateOfBirth":"Oct 16, 1973","age":"30","nationality":["England"],"currentClub":"Retired","height":"1,87m","foot":"left","joinedOn":"Aug 1, 1998","signedFrom":": Ablöse €4.60m"},{"id":"3589","name":"Gary Naysmith","position":"Left-Back","dateOfBirth":"Nov 16, 1978","age":"25","nationality":["Scotland"],"currentClub":"Retired","height":"1,78m","foot":"left","joinedOn":"Oct 1, 2000","signedFrom":"Heart of Midlothian FC"},{"id":"3309","name":"Steve Watson","position":"Right-Back","dateOfBirth":"Apr 1, 1974","age":"30","nationality":["England"],"currentClub":"Retired","height":"1,85m","foot":"right","joinedOn":"Jul 4, 2000","signedFrom":": Ablöse €3.75m"},{"id":"3614","name":"Tony Hibbert","position":"Right-Back","dateOfBirth":"Feb 20, 1981","age":"23","nationality":["England"],"currentClub":"Retired","height":"1,73m","foot":"right","joinedOn":"Jul 1, 2000","signedFrom":": Ablöse -"},{"id":"3590","name":"Tie Li","position":"Defensive Midfield","dateOfBirth":"May 18, 1977","age":"27","nationality":["China"],"currentClub":"Retired","height":"1,83m","foot":"right","joinedOn":"Jul 19, 2002","signedFrom":": Ablöse free transfer"},{"id":"301","name":"Thomas Gravesen","position":"Defensive Midfield","dateOfBirth":"Mar 11, 1976","age":"28","nationality":["Denmark"],"currentClub":"Retired","joinedOn":"Aug 1, 2007","signedFrom":"Celtic FC"},{"id":"3586","name":"Tobias Linderoth","position":"Defensive Midfield","dateOfBirth":"Apr 21, 1979","age":"25","nationality":["Sweden"],"currentClub":"Retired","height":"1,78m","foot":"right","joinedOn":"Jan 31, 2002","signedFrom":": Ablöse €3.75m"},{"id":"3618","name":"Lee Carsley","position":"Defensive Midfield","dateOfBirth":"Feb 28, 1974","age":"30","nationality":["Ireland","England"],"currentClub":"Retired","height":"1,78m","foot":"right","joinedOn":"Jan 1, 2003","signedFrom":"Coventry City"},{"id":"15304","name":"Steven Schumacher","position":"Central Midfield","dateOfBirth":"Apr 30, 1984","age":"20","nationality":["England"],"currentClub":"Retired","height":"1,83m","foot":"right","joinedOn":"Jul 1, 2002","signedFrom":": Ablöse -"},{"id":"3617","name":"Scot Gemmill","position":"Central Midfield","dateOfBirth":"Jan 2, 1971","age":"33","nationality":["Scotland"],"currentClub":"Retired","height":"1,81m","foot":"right","joinedOn":"Mar 25, 1999","signedFrom":": Ablöse €300k"},{"id":"3727","name":"Alex Nyarko","position":"Central Midfield","dateOfBirth":"Oct 15, 1973","age":"30","nationality":["Ghana","Switzerland"],"currentClub":"Retired","joinedOn":"Jul 1, 2000","signedFrom":": Ablöse €6.30m"},{"id":"3620","name":"Leon Osman","position":"Central Midfield","dateOfBirth":"May 17, 1981","age":"23","nationality":["England"],"currentClub":"Retired","height":"1,73m","foot":"right","joinedOn":"Jul 1, 2002","signedFrom":"Everton FC Reserves"},{"id":"3615","name":"Mark Pembridge","position":"Left Midfield","dateOfBirth":"Nov 29, 1970","age":"33","nationality":["Wales"],"currentClub":"Retired","joinedOn":"Aug 5, 1999","signedFrom":"SL Benfica"},{"id":"4135","name":"Kevin Kilbane","position":"Left Midfield","dateOfBirth":"Feb 1, 1977","age":"27","nationality":["Ireland","England"],"currentClub":"Retired","height":"1,83m","foot":"left","joinedOn":"Jul 1, 2003","signedFrom":"Sunderland AFC"},{"id":"9956","name":"James McFadden","position":"Second Striker","dateOfBirth":"Apr 14, 1983","age":"21","nationality":["Scotland"],"currentClub":"Retired","height":"1,78m","foot":"left","joinedOn":"Oct 17, 2011","signedFrom":"Without Club"},{"id":"3585","name":"Tomasz Radzinski","position":"Centre-Forward","dateOfBirth":"Dec 14, 1973","age":"30","nationality":["Canada","Poland"],"currentClub":"Retired","height":"1,74m","foot":"left","joinedOn":"Aug 20, 2001","signedFrom":": Ablöse €6.75m"},{"id":"3468","name":"Kevin Campbell","position":"Centre-Forward","dateOfBirth":"Feb 4, 1970","age":"34","nationality":["England","Jamaica"],"currentClub":"---","height":"1,83m","foot":"right","joinedOn":"Jul 23, 1999","signedFrom":"Trabzonspor"},{"id":"3239","name":"Duncan Ferguson","position":"Centre-Forward","dateOfBirth":"Dec 27, 1971","age":"32","nationality":["Scotland"],"currentClub":"Retired","height":"1,93m","foot":"left","joinedOn":"Jul 1, 2000","signedFrom":"Newcastle United"},{"id":"3186","name":"Francis Jeffers","position":"Centre-Forward","dateOfBirth":"Jan 25, 1981","age":"23","nationality":["England"],"currentClub":"Retired","height":"1,78m","foot":"right","joinedOn":"Sep 1, 2003","signedFrom":": Ablöse free transfer"},{"id":"3332","name":"Wayne Rooney","position":"Centre-Forward","dateOfBirth":"Oct 24, 1985","age":"18","nationality":["England"],"currentClub":"Retired","height":"1,76m","foot":"right","joinedOn":"Jul 9, 2017","signedFrom":"Manchester United"},{"id":"3616","name":"Nick Chadwick","position":"Centre-Forward","dateOfBirth":"Oct 26, 1982","age":"21","nationality":["England"],"currentClub":"Retired","height":"1,83m","foot":"right","joinedOn":"Jul 1, 2001","signedFrom":": Ablöse -"}],"updatedAt":"2024-11-11T02:22:54.027527"}