{"id":"985","players":[{"id":"3534","name":"Roy Carroll","position":"Goalkeeper","dateOfBirth":"Sep 30, 1977","age":"26","nationality":["Northern Ireland"],"currentClub":"Retired","height":"1,89m","foot":"right","joinedOn":"Jul 27, 2001","signedFrom":"Wigan Athletic"},{"id":"4267","name":"Tim Howard","position":"Goalkeeper","dateOfBirth":"Mar 6, 1979","age":"25","nationality":["United States","Hungary"],"currentClub":"Retired","height":"1,91m","foot":"right","joinedOn":"Jul 1, 2003","signedFrom":": Ablöse €3.20m"},{"id":"3539","name":"Luke Steele","position":"Goalkeeper","dateOfBirth":"Sep 24, 1984","age":"19","nationality":["England"],"currentClub":"Peterborough Sports","height":"1,88m","foot":"right","joinedOn":"Sep 1, 2001","signedFrom":"Peterborough United"},{"id":"3322","name":"Ben Williams","position":"Goalkeeper","dateOfBirth":"Aug 27, 1982","age":"21","nationality":["England"],"currentClub":"Retired","height":"1,88m","foot":"left"},{"id":"3235","name":"Rio Ferdinand","position":"Centre-Back","dateOfBirth":"Nov 7, 1978","age":"25","nationality":["England"],"currentClub":"Retired","height":"1,89m","foot":"right","joinedOn":"Jul 22, 2002","signedFrom":"Leeds United"},{"id":"3405","name":"Wes Brown","position":"Centre-Back","dateOfBirth":"Oct 13, 1979","age":"24","nationality":["England"],"currentClub":"Retired","height":"1,85m","foot":"right","joinedOn":"Jul 1, 1996","signedFrom":"Manchester United U18"},{"id":"3540","name":"John O'Shea","position":"Centre-Back","dateOfBirth":"Apr 30, 1981","age":"23","nationality":["Ireland"],"currentClub":"Retired","height":"1,92m","foot":"right","joinedOn":"Jul 1, 2001","signedFrom":"Manchester United Reserves"},{"id":"24637","name":"Jonathan Spector","position":"Centre-Back","dateOfBirth":"Mar 1, 1986","age":"18","nationality":["United States","Germany"],"currentClub":"Retired","height":"1,83m","foot":"right","joinedOn":"Jul 1, 2004","signedFrom":"Manchester United U18"},{"id":"3548","name":"Kieran Richardson","position":"Left-Back","dateOfBirth":"Oct 21, 1984","age":"19","nationality":["England"],"currentClub":"Retired","height":"1,77m","foot":"left","joinedOn":"Jul 1, 2001","signedFrom":": Ablöse free transfer"},{"id":"3541","name":"Quinton Fortune","position":"Left-Back","dateOfBirth":"May 21, 1977","age":"27","nationality":["South Africa","England"],"currentClub":"Retired","height":"1,82m","foot":"left","joinedOn":"Jan 1, 2000","signedFrom":": Ablöse €2.25m"},{"id":"3546","name":"Danny Pugh","position":"Left-Back","dateOfBirth":"Oct 19, 1982","age":"21","nationality":["England"],"currentClub":"Retired","joinedOn":"Jul 1, 2002","signedFrom":"Manchester United Reserves"},{"id":"3393","name":"Mikaël Silvestre","position":"Left-Back","dateOfBirth":"Aug 9, 1977","age":"26","nationality":["France","Guadeloupe"],"currentClub":"Retired","joinedOn":"Sep 10, 1999","signedFrom":": Ablöse €5.70m"},{"id":"4231","name":"Paul Tierney","position":"Left-Back","dateOfBirth":"Sep 15, 1982","age":"21","nationality":["Ireland","England"],"currentClub":"Unknown","height":"1,78m","foot":"left","joinedOn":"Jul 1, 2000","signedFrom":"Manchester United U18"},{"id":"3403","name":"Gary Neville","position":"Right-Back","dateOfBirth":"Feb 18, 1975","age":"29","nationality":["England"],"currentClub":"Retired","height":"1,80m","foot":"right","joinedOn":"Jul 1, 1992","signedFrom":"Manchester United U18"},{"id":"3404","name":"Phil Neville","position":"Right-Back","dateOfBirth":"Jan 21, 1977","age":"27","nationality":["England"],"currentClub":"Retired","height":"1,80m","foot":"right","joinedOn":"Jul 1, 1994","signedFrom":"Manchester United U18"},{"id":"3537","name":"Mark Lynch","position":"Right-Back","dateOfBirth":"Sep 2, 1981","age":"22","nationality":["England"],"currentClub":"Retired","height":"1,80m","foot":"right","joinedOn":"Jul 1, 2001","signedFrom":"Manchester United U18"},{"id":"15773","name":"Phil Bardsley","position":"Right-Back","dateOfBirth":"Jun 28, 1985","age":"19","nationality":["Scotland","England"],"currentClub":"Retired","height":"1,80m","foot":"right","joinedOn":"Jul 1, 2003","signedFrom":"Manchester United U18"},{"id":"3543","name":"Nicky Butt","position":"Defensive Midfield","dateOfBirth":"Jan 21, 1975","age":"29","nationality":["England"],"currentClub":"Retired","height":"1,78m","foot":"right","joinedOn":"Jul 1, 1992","signedFrom":"Manchester United U18"},{"id":"5509","name":"Eric Djemba Djemba","position":"Defensive Midfield","dateOfBirth":"May 4, 1981","age":"23","nationality":["Cameroon","France"],"currentClub":"Retired","height":"1,77m","foot":"right","joinedOn":"Jul 1, 2003","signedFrom":": Ablöse €4.50m"},{"id":"3365","name":"Kléberson","position":"Central Midfield","dateOfBirth":"Jun 19, 1979","age":"25","nationality":["Brazil"],"currentClub":"Retired","height":"1,75m","foot":"right","joinedOn":"Jul 1, 2003","signedFrom":": Ablöse €8.60m"},{"id":"3396","name":"Roy Keane","position":"Central Midfield","dateOfBirth":"Aug 10, 1971","age":"32","nationality":["Ireland"],"currentClub":"Retired","joinedOn":"Jul 1, 1993","signedFrom":": Ablöse €4.40m"},{"id":"3397","name":"Paul Scholes","position":"Central Midfield","dateOfBirth":"Nov 16, 1974","age":"29","nationality":["England"],"currentClub":"Retired","height":"1,68m","foot":"right","joinedOn":"Jan 8, 2012"},{"id":"3547","name":"Darren Fletcher","position":"Central Midfield","dateOfBirth":"Feb 1, 1984","age":"20","nationality":["Scotland"],"currentClub":"Retired","height":"1,84m","foot":"right","joinedOn":"Jul 1, 2001","signedFrom":"Manchester United U18"},{"id":"24634","name":"David Jones","position":"Central Midfield","dateOfBirth":"Nov 4, 1984","age":"19","nationality":["England","Wales"],"currentClub":"Retired","height":"1,83m","foot":"left","joinedOn":"Jul 1, 2004","signedFrom":"Manchester United Reserves"},{"id":"11320","name":"Neil Wood","position":"Central Midfield","dateOfBirth":"Jan 4, 1983","age":"21","nationality":["England"],"currentClub":"Retired","height":"1,77m","foot":"left"},{"id":"3406","name":"Ryan Giggs","position":"Left Midfield","dateOfBirth":"Nov 29, 1973","age":"30","nationality":["Wales"],"currentClub":"Retired","height":"1,79m","foot":"left","joinedOn":"Jul 1, 1991","signedFrom":"Manchester United U18"},{"id":"24635","name":"Chris Eagles","position":"Right Winger","dateOfBirth":"Nov 19, 1985","age":"18","nationality":["England"],"currentClub":"Retired","height":"1,83m","foot":"right","joinedOn":"Jul 25, 2003","signedFrom":"Manchester United U18"},{"id":"8198","name":"Cristiano Ronaldo","position":"Centre-Forward","dateOfBirth":"Feb 5, 1985","age":"19","nationality":["Portugal"],"currentClub":"Al-Nassr FC","height":"1,88m","foot":"right","joinedOn":"Aug 31, 2021","signedFrom":"Juventus FC"},{"id":"4015","name":"Louis Saha","position":"Centre-Forward","dateOfBirth":"Aug 8, 1978","age":"25","nationality":["France","Guadeloupe"],"currentClub":"Retired","height":"1,82m","foot":"left","joinedOn":"Jan 23, 2004","signedFrom":"Fulham FC"},{"id":"3407","name":"Ruud van Nistelrooy","position":"Centre-Forward","dateOfBirth":"Jul 1, 1976","age":"27","nationality":["Netherlands"],"currentClub":"Retired","height":"1,89m","foot":"right","joinedOn":"Jul 1, 2001","signedFrom":": Ablöse €28.50m"},{"id":"3115","name":"David Bellion","position":"Centre-Forward","dateOfBirth":"Nov 27, 1982","age":"21","nationality":["France","Senegal"],"currentClub":"Retired","height":"1,81m","foot":"right","joinedOn":"Jul 1, 2003","signedFrom":"Sunderland AFC"},{"id":"3394","name":"Ole Gunnar Solskjær","position":"Centre-Forward","dateOfBirth":"Feb 26, 1973","age":"31","nationality":["Norway"],"currentClub":"Retired","height":"1,79m","foot":"both","joinedOn":"Jul 29, 1996","signedFrom":"Molde FK"},{"id":"3408","name":"Diego Forlán","position":"Centre-Forward","dateOfBirth":"May 19, 1979","age":"25","nationality":["Uruguay","Spain"],"currentClub":"Retired","joinedOn":"Jan 20, 2002","signedFrom":"CA Independiente"},{"id":"15997","name":"Eddie Johnson","position":"Centre-Forward","dateOfBirth":"Sep 20, 1984","age":"19","nationality":["England"],"currentClub":"Retired","height":"1,78m","foot":"right","joinedOn":"Jul 1, 2001","signedFrom":"Manchester United U18"},{"id":"3536","name":"Daniel Nardiello","position":"Centre-Forward","dateOfBirth":"Oct 22, 1982","age":"21","nationality":["Wales","England"],"currentClub":"Retired","height":"1,80m"}],"updatedAt":"2024-11-11T02:25:41.011727"}