{"id":"337","players":[{"id":"13572","name":"Ben Foster","position":"Goalkeeper","dateOfBirth":"Apr 3, 1983","age":"28","nationality":["England"],"currentClub":"Retired","height":"1,93m","foot":"left","joinedOn":"Jul 1, 2010","signedFrom":"Manchester United","marketValue":"€5.00m"},{"id":"28728","name":"Colin Doyle","position":"Goalkeeper","dateOfBirth":"Jun 12, 1985","age":"26","nationality":["Ireland"],"currentClub":"Bradford City","height":"1,96m","foot":"right","joinedOn":"Jul 1, 2003","signedFrom":"Birmingham City U18","marketValue":"€250k"},{"id":"3723","name":"Maik Taylor","position":"Goalkeeper","dateOfBirth":"Sep 4, 1971","age":"39","nationality":["Northern Ireland","Germany"],"currentClub":"Retired","height":"1,93m","foot":"right","joinedOn":"Mar 22, 2004","signedFrom":"Fulham FC"},{"id":"42751","name":"Roger Johnson","position":"Centre-Back","dateOfBirth":"Apr 28, 1983","age":"28","nationality":["England"],"currentClub":"Retired","height":"1,91m","foot":"right","joinedOn":"Jul 1, 2009","signedFrom":": Ablöse €5.90m","marketValue":"€5.00m"},{"id":"4070","name":"Liam Ridgewell","position":"Centre-Back","dateOfBirth":"Jul 21, 1984","age":"26","nationality":["England"],"currentClub":"Retired","height":"1,88m","foot":"both","joinedOn":"Aug 3, 2007","signedFrom":": Ablöse €3.00m","marketValue":"€4.50m"},{"id":"62688","name":"Scott Dann","position":"Centre-Back","dateOfBirth":"Feb 14, 1987","age":"24","nationality":["England"],"currentClub":"Without Club","height":"1,94m","foot":"right","joinedOn":"Jul 1, 2009","signedFrom":"Coventry City","marketValue":"€4.50m"},{"id":"18227","name":"Curtis Davies","position":"Centre-Back","dateOfBirth":"Mar 15, 1985","age":"26","nationality":["Sierra Leone","England"],"currentClub":"Retired","height":"1,88m","foot":"right","joinedOn":"Jan 28, 2011","signedFrom":": Ablöse €4.00m","marketValue":"€4.50m"},{"id":"6065","name":"Martin Jiranek","position":"Centre-Back","dateOfBirth":"May 25, 1979","age":"32","nationality":["Czech Republic"],"currentClub":"Retired","height":"1,90m","foot":"right","joinedOn":"Aug 30, 2010","signedFrom":": Ablöse €600k","marketValue":"€2.00m"},{"id":"138736","name":"Alpaslan Öztürk","position":"Centre-Back","dateOfBirth":"Jul 16, 1993","age":"17","nationality":["Türkiye","Belgium"],"currentClub":"Pendikspor","height":"1,86m","foot":"right"},{"id":"120967","name":"Fraser Kerr","position":"Centre-Back","dateOfBirth":"Jan 17, 1993","age":"18","nationality":["Scotland"],"currentClub":"AFC Telford United","height":"1,91m","foot":"right"},{"id":"18871","name":"Jean Beausejour","position":"Left-Back","dateOfBirth":"Jun 1, 1984","age":"27","nationality":["Chile","Haiti"],"currentClub":"Retired","height":"1,78m","foot":"left","joinedOn":"Aug 30, 2010","signedFrom":"CF América","marketValue":"€2.50m"},{"id":"3868","name":"David Murphy","position":"Left-Back","dateOfBirth":"Mar 1, 1984","age":"27","nationality":["England"],"currentClub":"Retired","height":"1,85m","foot":"left","joinedOn":"Jan 1, 2008","signedFrom":"Hibernian FC","marketValue":"€750k"},{"id":"4046","name":"Stephen Carr","position":"Right-Back","dateOfBirth":"Aug 29, 1976","age":"34","nationality":["Ireland"],"currentClub":"Retired","height":"1,75m","foot":"right","joinedOn":"Jan 1, 2009","marketValue":"€1.50m"},{"id":"3866","name":"Stuart Parnaby","position":"Right-Back","dateOfBirth":"Jul 19, 1982","age":"28","nationality":["England"],"currentClub":"Retired","height":"1,78m","foot":"right","joinedOn":"Jul 1, 2007","signedFrom":"Middlesbrough FC","marketValue":"€1.00m"},{"id":"10251","name":"Barry Ferguson","position":"Defensive Midfield","dateOfBirth":"Feb 2, 1978","age":"33","nationality":["Scotland"],"currentClub":"Retired","height":"1,78m","foot":"right","joinedOn":"Jul 17, 2009","signedFrom":": Ablöse €1.20m","marketValue":"€4.50m"},{"id":"31720","name":"Sebastian Larsson","position":"Central Midfield","dateOfBirth":"Jun 6, 1985","age":"26","nationality":["Sweden"],"currentClub":"Retired","height":"1,78m","foot":"right","joinedOn":"Jan 31, 2007","signedFrom":": Ablöse €1.50m","marketValue":"€6.00m"},{"id":"37171","name":"Craig Gardner","position":"Central Midfield","dateOfBirth":"Nov 25, 1986","age":"24","nationality":["England"],"currentClub":"Retired","height":"1,76m","foot":"right","joinedOn":"Jul 1, 2017","signedFrom":"West Bromwich Albion","marketValue":"€4.00m"},{"id":"3877","name":"Lee Bowyer","position":"Central Midfield","dateOfBirth":"Jan 3, 1977","age":"34","nationality":["England"],"currentClub":"Retired","height":"1,75m","foot":"right","joinedOn":"Jul 8, 2009","signedFrom":": Ablöse free transfer","marketValue":"€2.50m"},{"id":"57818","name":"Míchel Madera","position":"Central Midfield","dateOfBirth":"Nov 8, 1985","age":"25","nationality":["Spain"],"currentClub":"Retired","height":"1,83m","foot":"right","joinedOn":"Jan 11, 2010","signedFrom":"Sporting Gijón","marketValue":"€2.50m"},{"id":"29878","name":"Keith Fahey","position":"Central Midfield","dateOfBirth":"Jan 15, 1983","age":"28","nationality":["Ireland"],"currentClub":"Retired","height":"1,79m","foot":"right","joinedOn":"Jan 1, 2009","signedFrom":"St. Patrick's Athletic","marketValue":"€2.50m"},{"id":"57207","name":"Jordon Mutch","position":"Central Midfield","dateOfBirth":"Dec 2, 1991","age":"19","nationality":["England"],"currentClub":"Gold Coast Knights","height":"1,84m","foot":"right","joinedOn":"Jul 1, 2009","signedFrom":"Birmingham City U18","marketValue":"€500k"},{"id":"65305","name":"Enric Vallès","position":"Central Midfield","dateOfBirth":"Mar 1, 1990","age":"21","nationality":["Spain"],"currentClub":"Unknown","height":"1,90m","foot":"right","joinedOn":"Jul 1, 2010","signedFrom":": Ablöse free transfer","marketValue":"€75k"},{"id":"3205","name":"David Bentley","position":"Right Midfield","dateOfBirth":"Aug 27, 1984","age":"26","nationality":["England"],"currentClub":"Retired","height":"1,78m","foot":"right","joinedOn":"Jan 12, 2011","signedFrom":"Tottenham Hotspur","marketValue":"€7.00m"},{"id":"597","name":"Aleksandr Hleb","position":"Attacking Midfield","dateOfBirth":"May 1, 1981","age":"30","nationality":["Belarus"],"currentClub":"Retired","joinedOn":"Aug 31, 2010","signedFrom":"FC Barcelona","marketValue":"€5.00m"},{"id":"129078","name":"Nathan Redmond","position":"Right Winger","dateOfBirth":"Mar 6, 1994","age":"17","nationality":["England","Jamaica"],"currentClub":"Burnley FC","height":"1,73m","foot":"right","joinedOn":"Jul 1, 2011","signedFrom":"Birmingham City U18","marketValue":"€50k","status":"Hamstring injury - Return unknown"},{"id":"9956","name":"James McFadden","position":"Second Striker","dateOfBirth":"Apr 14, 1983","age":"28","nationality":["Scotland"],"currentClub":"Retired","height":"1,78m","foot":"left","joinedOn":"Jan 18, 2008","signedFrom":": Ablöse €7.50m","marketValue":"€4.00m"},{"id":"5794","name":"Obafemi Martins","position":"Centre-Forward","dateOfBirth":"Oct 28, 1984","age":"26","nationality":["Nigeria","Italy"],"currentClub":"Retired","joinedOn":"Jan 31, 2011","signedFrom":": Ablöse €400k","marketValue":"€7.00m"},{"id":"19729","name":"Nikola Zigic","position":"Centre-Forward","dateOfBirth":"Sep 25, 1980","age":"30","nationality":["Serbia"],"currentClub":"Retired","height":"2,02m","foot":"right","joinedOn":"Dec 5, 2014","signedFrom":"Without Club","marketValue":"€6.00m"},{"id":"35855","name":"Cameron Jerome","position":"Centre-Forward","dateOfBirth":"Aug 14, 1986","age":"24","nationality":["Grenada","England"],"currentClub":"Without Club","height":"1,85m","foot":"right","joinedOn":"Jul 1, 2006","signedFrom":": Ablöse €4.45m","marketValue":"€5.50m"},{"id":"15175","name":"Matt Derbyshire","position":"Centre-Forward","dateOfBirth":"Apr 14, 1986","age":"25","nationality":["England"],"currentClub":"Retired","height":"1,80m","foot":"right","joinedOn":"Aug 16, 2010","signedFrom":": Ablöse €600k","marketValue":"€3.50m"},{"id":"15708","name":"Garry O'Connor","position":"Centre-Forward","dateOfBirth":"May 7, 1983","age":"28","nationality":["Scotland"],"currentClub":"Retired","height":"1,86m","foot":"right","joinedOn":"Jul 1, 2007","signedFrom":": Ablöse €4.00m","marketValue":"€1.50m"},{"id":"9958","name":"Marcus Bent","position":"Centre-Forward","dateOfBirth":"May 19, 1978","age":"33","nationality":["England","Jamaica"],"currentClub":"Cornard United FC","height":"1,88m","foot":"right","joinedOn":"Jul 1, 2008","signedFrom":"Charlton Athletic","marketValue":"€1.00m"},{"id":"3131","name":"Kevin Phillips","position":"Centre-Forward","dateOfBirth":"Jul 25, 1973","age":"37","nationality":["England"],"currentClub":"Retired","height":"1,70m","foot":"right","joinedOn":"Jul 9, 2008","signedFrom":"West Bromwich Albion","marketValue":"€750k"},{"id":"129552","name":"Akwasi Asante","position":"Centre-Forward","dateOfBirth":"Sep 6, 1992","age":"18","nationality":["Netherlands","Ghana"],"currentClub":"Without Club","height":"1,83m","foot":"right","joinedOn":"Jul 1, 2011","signedFrom":"Birmingham City U18"}],"updatedAt":"2024-11-11T02:31:48.409196"}