{"id":"289","players":[{"id":"12589","name":"Craig Gordon","position":"Goalkeeper","dateOfBirth":"Dec 31, 1982","age":"25","nationality":["Scotland"],"currentClub":"Heart of Midlothian FC","height":"1,93m","foot":"left","joinedOn":"Aug 8, 2007","signedFrom":"Heart of Midlothian FC","marketValue":"€7.25m"},{"id":"9993","name":"Darren Ward","position":"Goalkeeper","dateOfBirth":"May 11, 1974","age":"34","nationality":["Wales"],"currentClub":"Retired","height":"1,80m","joinedOn":"Jul 1, 2006","signedFrom":": Ablöse free transfer","marketValue":"€850k"},{"id":"17879","name":"Márton Fülöp","position":"Goalkeeper","dateOfBirth":"May 3, 1983","age":"25","nationality":["Hungary"],"currentClub":"---","height":"1,98m","foot":"right","joinedOn":"Jan 2, 2007","signedFrom":"Tottenham Hotspur","marketValue":"€750k"},{"id":"41131","name":"Trevor Carson","position":"Goalkeeper","dateOfBirth":"Mar 5, 1988","age":"20","nationality":["Northern Ireland"],"currentClub":"Dundee FC","height":"1,85m","foot":"right","joinedOn":"Jul 1, 2006","signedFrom":"Sunderland AFC U18","marketValue":"€100k"},{"id":"24636","name":"Paul McShane","position":"Centre-Back","dateOfBirth":"Jan 6, 1986","age":"22","nationality":["Ireland"],"currentClub":"Retired","height":"1,83m","foot":"right","joinedOn":"Jul 26, 2007","signedFrom":"West Bromwich Albion","marketValue":"€3.75m"},{"id":"3686","name":"Danny Higginbotham","position":"Centre-Back","dateOfBirth":"Dec 29, 1978","age":"29","nationality":["Gibraltar","England"],"currentClub":"Retired","height":"1,85m","foot":"left","joinedOn":"Aug 29, 2007","signedFrom":"Stoke City","marketValue":"€3.25m"},{"id":"42062","name":"Greg Halford","position":"Centre-Back","dateOfBirth":"Dec 8, 1984","age":"23","nationality":["England"],"currentClub":"Blyth Spartans","height":"1,93m","foot":"right","joinedOn":"Jul 1, 2007","signedFrom":"Reading FC","marketValue":"€3.00m"},{"id":"14054","name":"Nyron Nosworthy","position":"Centre-Back","dateOfBirth":"Oct 11, 1980","age":"27","nationality":["Jamaica","England"],"currentClub":"Retired","height":"1,85m","foot":"right","joinedOn":"Jul 1, 2005","signedFrom":"Gillingham FC","marketValue":"€2.00m"},{"id":"26183","name":"Danny Collins","position":"Centre-Back","dateOfBirth":"Aug 6, 1980","age":"27","nationality":["Wales","England"],"currentClub":"Retired","height":"1,85m","foot":"left","joinedOn":"Oct 1, 2004","signedFrom":"Chester City (- 2010)","marketValue":"€2.00m"},{"id":"9495","name":"Stanislav Varga","position":"Centre-Back","dateOfBirth":"Oct 8, 1972","age":"35","nationality":["Slovakia","Hungary"],"currentClub":"Retired","height":"1,93m","foot":"right","joinedOn":"Aug 1, 2006","signedFrom":"Celtic FC","marketValue":"€1.00m"},{"id":"12765","name":"Russell Anderson","position":"Centre-Back","dateOfBirth":"Oct 25, 1978","age":"29","nationality":["Scotland"],"currentClub":"Retired","height":"1,86m","foot":"right","joinedOn":"Jul 1, 2007","signedFrom":"Aberdeen FC","marketValue":"€850k"},{"id":"42412","name":"Jonny Evans","position":"Centre-Back","dateOfBirth":"Jan 3, 1988","age":"20","nationality":["Northern Ireland"],"currentClub":"Manchester United","height":"1,88m","foot":"both","joinedOn":"Jan 4, 2008","signedFrom":"Manchester United","marketValue":"€500k"},{"id":"55381","name":"Jean-Yves M'voto","position":"Centre-Back","dateOfBirth":"Sep 6, 1988","age":"19","nationality":["France","Cameroon"],"currentClub":"Retired","height":"1,94m","foot":"right","joinedOn":"Jan 15, 2008","signedFrom":": Ablöse €400k","marketValue":"€400k"},{"id":"64885","name":"Jack Pelter","position":"Centre-Back","dateOfBirth":"Jul 30, 1987","age":"20","nationality":["New Zealand","England"],"currentClub":"Metro FC","height":"1,87m","foot":"right","joinedOn":"Sep 1, 2007","signedFrom":"Without Club","marketValue":"€100k"},{"id":"41132","name":"Peter Hartley","position":"Centre-Back","dateOfBirth":"Apr 3, 1988","age":"20","nationality":["England"],"currentClub":"Retired","height":"1,87m","foot":"left","marketValue":"€100k"},{"id":"3548","name":"Kieran Richardson","position":"Left-Back","dateOfBirth":"Oct 21, 1984","age":"23","nationality":["England"],"currentClub":"Retired","height":"1,77m","foot":"left","joinedOn":"Jul 16, 2007","signedFrom":"Manchester United","marketValue":"€6.00m"},{"id":"3634","name":"Ian Harte","position":"Left-Back","dateOfBirth":"Aug 31, 1977","age":"30","nationality":["Ireland"],"currentClub":"Retired","height":"1,75m","foot":"left","joinedOn":"Aug 1, 2007","signedFrom":": Ablöse free transfer","marketValue":"€2.00m"},{"id":"60106","name":"Gavin Donoghue","position":"Left-Back","dateOfBirth":"Mar 3, 1989","age":"19","nationality":["Ireland"],"currentClub":"Retired","height":"1,80m","foot":"left","joinedOn":"Jul 1, 2007","signedFrom":"Sunderland AFC U18","marketValue":"€100k"},{"id":"15773","name":"Phil Bardsley","position":"Right-Back","dateOfBirth":"Jun 28, 1985","age":"23","nationality":["Scotland","England"],"currentClub":"Retired","height":"1,80m","foot":"right","joinedOn":"Jan 22, 2008","signedFrom":"Manchester United","marketValue":"€3.00m"},{"id":"33489","name":"Carlos Edwards","position":"Right-Back","dateOfBirth":"Oct 24, 1978","age":"29","nationality":["Trinidad and Tobago"],"currentClub":"FC Hadleigh United","height":"1,80m","foot":"right","joinedOn":"Jan 2, 2007","signedFrom":": Ablöse €2.10m","marketValue":"€2.00m"},{"id":"4126","name":"Stephen Wright","position":"Right-Back","dateOfBirth":"Feb 8, 1980","age":"28","nationality":["England"],"currentClub":"Retired","height":"1,83m","foot":"right","joinedOn":"Aug 15, 2002","signedFrom":": Ablöse €4.80m","marketValue":"€1.50m"},{"id":"14011","name":"Dickson Etuhu","position":"Defensive Midfield","dateOfBirth":"Jun 8, 1982","age":"26","nationality":["Nigeria","England"],"currentClub":"Retired","height":"1,89m","foot":"right","joinedOn":"Jul 17, 2007","signedFrom":": Ablöse €2.00m","marketValue":"€2.50m"},{"id":"21804","name":"Robbie Weir","position":"Defensive Midfield","dateOfBirth":"Dec 9, 1988","age":"19","nationality":["Northern Ireland"],"currentClub":"Crusaders FC","height":"1,75m","foot":"left","joinedOn":"Jul 1, 2009","signedFrom":"Sunderland AFC Reserves","marketValue":"€100k"},{"id":"9505","name":"Liam Miller","position":"Central Midfield","dateOfBirth":"Feb 13, 1981","age":"27","nationality":["Ireland"],"currentClub":"---","height":"1,73m","foot":"right","joinedOn":"Jul 1, 2006","signedFrom":"Manchester United","marketValue":"€2.00m"},{"id":"13796","name":"Grant Leadbitter","position":"Central Midfield","dateOfBirth":"Jan 7, 1986","age":"22","nationality":["England"],"currentClub":"Retired","height":"1,77m","foot":"right","joinedOn":"Jan 29, 2019","signedFrom":"Middlesbrough FC","marketValue":"€2.00m"},{"id":"13683","name":"Dean Whitehead","position":"Central Midfield","dateOfBirth":"Jan 12, 1982","age":"26","nationality":["England"],"currentClub":"Retired","height":"1,83m","foot":"right","joinedOn":"Jul 1, 2004","signedFrom":": Ablöse €300k","marketValue":"€1.50m"},{"id":"12712","name":"Graham Kavanagh","position":"Central Midfield","dateOfBirth":"Dec 2, 1973","age":"34","nationality":["Ireland"],"currentClub":"Retired","joinedOn":"Aug 1, 2006","signedFrom":"Wigan Athletic","marketValue":"€600k"},{"id":"60104","name":"Jamie Chandler","position":"Central Midfield","dateOfBirth":"Mar 24, 1989","age":"19","nationality":["England"],"currentClub":"Retired","height":"1,70m","foot":"right","marketValue":"€100k"},{"id":"7045","name":"Jake Richardson","position":"Central Midfield","dateOfBirth":"Oct 22, 1988","age":"19","nationality":["England"],"currentClub":"Retired","height":"1,71m","foot":"right","joinedOn":"Jul 1, 2005","signedFrom":"Sunderland AFC U18"},{"id":"9509","name":"Ross Wallace","position":"Right Midfield","dateOfBirth":"May 23, 1985","age":"23","nationality":["Scotland"],"currentClub":"Retired","height":"1,68m","foot":"left","joinedOn":"Aug 31, 2006","signedFrom":"Celtic FC","marketValue":"€2.50m"},{"id":"10008","name":"Andy Reid","position":"Left Midfield","dateOfBirth":"Jul 29, 1982","age":"25","nationality":["Ireland"],"currentClub":"Retired","height":"1,70m","foot":"left","joinedOn":"Jan 1, 2008","signedFrom":"Charlton Athletic","marketValue":"€4.75m","status":"Groin injury - Return unknown"},{"id":"60105","name":"Billy Dennehy","position":"Left Midfield","dateOfBirth":"Feb 17, 1987","age":"21","nationality":["Ireland"],"currentClub":"Retired","height":"1,73m","foot":"left","joinedOn":"Jul 1, 2007","signedFrom":"Sunderland AFC U18","marketValue":"€100k"},{"id":"7919","name":"Arnau Riera","position":"Left Winger","dateOfBirth":"Oct 1, 1981","age":"26","nationality":["Spain"],"currentClub":"Retired","height":"1,74m","foot":"left","joinedOn":"Jul 1, 2006","signedFrom":"FC Barcelona B","marketValue":"€750k"},{"id":"28245","name":"Kenwyne Jones","position":"Centre-Forward","dateOfBirth":"Oct 5, 1984","age":"23","nationality":["Trinidad and Tobago"],"currentClub":"Retired","height":"1,87m","foot":"right","joinedOn":"Aug 1, 2007","signedFrom":"Southampton FC","marketValue":"€9.00m"},{"id":"3463","name":"Michael Chopra","position":"Centre-Forward","dateOfBirth":"Dec 23, 1983","age":"24","nationality":["England","India"],"currentClub":"Without Club","height":"1,75m","foot":"right","joinedOn":"Jul 13, 2007","signedFrom":": Ablöse €7.50m","marketValue":"€5.50m"},{"id":"1610","name":"Rade Prica","position":"Centre-Forward","dateOfBirth":"Jun 30, 1980","age":"28","nationality":["Sweden","Croatia"],"currentClub":"Retired","height":"1,85m","foot":"right","joinedOn":"Jan 1, 2008","signedFrom":"Aalborg BK","marketValue":"€2.75m"},{"id":"35587","name":"Anthony Stokes","position":"Centre-Forward","dateOfBirth":"Jul 25, 1988","age":"19","nationality":["Ireland"],"currentClub":"Retired","height":"1,85m","foot":"right","joinedOn":"Jan 8, 2007","signedFrom":"Arsenal FC Reserves","marketValue":"€2.50m"},{"id":"31312","name":"Daryl Murphy","position":"Centre-Forward","dateOfBirth":"Mar 15, 1983","age":"25","nationality":["Ireland"],"currentClub":"Retired","height":"1,89m","foot":"left","joinedOn":"Jul 1, 2005","signedFrom":": Ablöse €150k","marketValue":"€1.75m"},{"id":"3793","name":"Stern John","position":"Centre-Forward","dateOfBirth":"Oct 30, 1976","age":"31","nationality":["Trinidad and Tobago"],"currentClub":"Retired","height":"1,85m","foot":"right","joinedOn":"Jan 29, 2007","signedFrom":"Coventry City","marketValue":"€1.25m"},{"id":"9051","name":"David Connolly","position":"Centre-Forward","dateOfBirth":"Jun 6, 1977","age":"31","nationality":["Ireland"],"currentClub":"Retired","height":"1,75m","foot":"right","joinedOn":"Aug 1, 2006","signedFrom":"Wigan Athletic","marketValue":"€1.00m"},{"id":"3223","name":"Dwight Yorke","position":"Centre-Forward","dateOfBirth":"Nov 3, 1971","age":"36","nationality":["Trinidad and Tobago","England"],"currentClub":"Retired","height":"1,78m","joinedOn":"Jul 1, 2006","signedFrom":": Ablöse €300k","marketValue":"€800k"},{"id":"3238","name":"Andy Cole","position":"Centre-Forward","dateOfBirth":"Oct 15, 1971","age":"36","nationality":["England","Jamaica"],"currentClub":"Retired","height":"1,75m","foot":"right","joinedOn":"Aug 24, 2007","signedFrom":": Ablöse free transfer","marketValue":"€800k"},{"id":"34629","name":"Roy O'Donovan","position":"Centre-Forward","dateOfBirth":"Aug 10, 1985","age":"22","nationality":["Ireland","Australia"],"currentClub":"Retired","height":"1,79m","foot":"right","joinedOn":"Jul 1, 2007","signedFrom":"Cork City FC","marketValue":"€700k"},{"id":"60107","name":"David Dowson","position":"Centre-Forward","dateOfBirth":"Sep 12, 1988","age":"19","nationality":["England"],"currentClub":"Without Club","height":"1,78m","foot":"right","marketValue":"€100k"},{"id":"61674","name":"Martyn Waghorn","position":"Centre-Forward","dateOfBirth":"Jan 23, 1990","age":"18","nationality":["England"],"currentClub":"Northampton Town","height":"1,77m","foot":"left","joinedOn":"Jul 1, 2008","signedFrom":"Sunderland AFC U18","marketValue":"€50k"}],"updatedAt":"2024-11-11T02:30:01.699224"}